binlock/__init__.py
binlock/_binlock.py
binlock/defaults.py
binlock/exceptions.py
pybinlock-0.7.0.dist-info/LICENSE
pybinlock-0.7.0.dist-info/METADATA
pybinlock-0.7.0.dist-info/WHEEL
pybinlock-0.7.0.dist-info/top_level.txt
pybinlock-0.7.0.dist-info/RECORD
