Metadata-Version: 2.2
Name: pybinlock
Version: 0.7.0
Summary: A python package for programmatically reading, writing, and managing Avid Media Composer bin locks (`.lck` files).
Author-email: Michael Jordan <michael@glowingpixel.com>
Project-URL: Homepage, https://github.com/mjiggidy/pybinlock/
Project-URL: Repository, https://github.com/mjiggidy/pybinlock.git
Project-URL: Changelog, https://github.com/mjiggidy/pybinlock/releases/
Project-URL: Documentation, https://pybinlock.readthedocs.io/
Project-URL: Issues, https://github.com/mjiggidy/pybinlock/issues/
Keywords: avid,media composer,nle,editorial,post,production,film,television,nexis,avb,bins,lock,lck
Classifier: Development Status :: 4 - Beta
Classifier: Intended Audience :: Developers
Classifier: Intended Audience :: Telecommunications Industry
Classifier: Intended Audience :: Other Audience
Classifier: License :: OSI Approved :: GNU General Public License v3 or later (GPLv3+)
Classifier: Operating System :: OS Independent
Classifier: Programming Language :: Python :: 3
Classifier: Topic :: File Formats
Classifier: Topic :: Multimedia
Classifier: Topic :: Multimedia :: Video :: Non-Linear Editor
Classifier: Topic :: Utilities
Requires-Python: >=3.6
License-File: LICENSE
